synthizer/py.typed
synthizer/synthizer.cp314-win_amd64.pyd
synthizer/synthizer.cpp
synthizer/synthizer.pxd
synthizer/synthizer.pyi
synthizer/synthizer.pyx
synthizer/synthizer_constants.pxd
synthizer/__init__.py
synthizer/__init__.pyi
synthizer3d-0.14.3.dist-info/DELVEWHEEL
synthizer3d-0.14.3.dist-info/METADATA
synthizer3d-0.14.3.dist-info/RECORD
synthizer3d-0.14.3.dist-info/top_level.txt
synthizer3d-0.14.3.dist-info/WHEEL
synthizer3d-0.14.3.dist-info/licenses/LICENSE
synthizer3d.libs/faad-2-653e77768ed2799f4ab9075d31ab618f.dll
synthizer3d.libs/ogg-224e3f214a0bb6d4cb642367a1ec9633.dll
synthizer3d.libs/opus-50c730ae482a6d97480bf40c1af8ea65.dll
synthizer3d.libs/SoundTouch-6766862dc3e61fe695b186dfb40dc6b5.dll
synthizer3d.libs/vorbis-9dbb62fa1f4aca815a20dd2fd31e4d42.dll
synthizer3d.libs/vorbisfile-37342c33bc4124214041bc771446a879.dll
