Metadata-Version: 2.4
Name: synthizer3d
Version: 0.14.3
Summary: A 3D audio library for Python, forked and maintained by Ambro86. Originally developed by Synthizer Developers.
Home-page: https://github.com/Ambro86/synthizer3d
Author: Ambro86, originally by Synthizer Developers
Author-email: ambro86@gmail.com
License-File: LICENSE
Dynamic: author
Dynamic: author-email
Dynamic: description
Dynamic: description-content-type
Dynamic: home-page
Dynamic: license-file
Dynamic: summary
